caerus/__init__.py
caerus/caerus.py
caerus/examples.py
caerus/helper.py
caerus/data/__init__.py
caerus-1.0.1.dist-info/licenses/LICENSE
caerus-1.0.1.dist-info/METADATA
caerus-1.0.1.dist-info/WHEEL
caerus-1.0.1.dist-info/top_level.txt
caerus-1.0.1.dist-info/RECORD
