Metadata-Version: 2.4
Name: caerus
Version: 1.0.1
Summary: caerus is a Python library for peak detection.
Author-email: Erdogan Taskesen <erdogant@gmail.com>
License-Expression: MIT
Project-URL: Homepage, https://erdogant.github.io/caerus
Project-URL: Download, https://github.com/erdogant/caerus/archive/{version}.tar.gz
Keywords: Python,peak detection,signal processing,stocks,TA,Technical Analysis
Classifier: Programming Language :: Python :: 3
Classifier: Intended Audience :: Education
Classifier: Intended Audience :: Science/Research
Classifier: Operating System :: Unix
Classifier: Operating System :: Microsoft :: Windows
Classifier: Operating System :: MacOS
Classifier: Operating System :: OS Independent
Classifier: Topic :: Scientific/Engineering :: Artificial Intelligence
Requires-Python: >=3
License-File: LICENSE
Requires-Dist: numpy
Requires-Dist: matplotlib>=3.5.2
Requires-Dist: tqdm
Requires-Dist: datazets
Dynamic: license-file
